pybirdsreynolds/DESCRIPTION.txt
pybirdsreynolds/EPILOG.txt
pybirdsreynolds/__init__.py
pybirdsreynolds/app.py
pybirdsreynolds/args.py
pybirdsreynolds/const.py
pybirdsreynolds/controls.py
pybirdsreynolds/draw.py
pybirdsreynolds/params.py
pybirdsreynolds/reynolds.py
pybirdsreynolds/variables.py
pybirdsreynolds-3.0.0.dist-info/METADATA
pybirdsreynolds-3.0.0.dist-info/WHEEL
pybirdsreynolds-3.0.0.dist-info/entry_points.txt
pybirdsreynolds-3.0.0.dist-info/top_level.txt
pybirdsreynolds-3.0.0.dist-info/RECORD
