Metadata-Version: 2.4
Name: pybirdsreynolds
Version: 3.0.0
Summary: this project is an interactive simulation of the Reynolds Boids model, implemented in Python with Tkinter. It allows you to visualize and experiment with the collective behavior of a flock of virtual birds by adjusting parameters such as cohesion, alignment, separation, speed, and neighborhood radius in real time. The interface also provides several controls (pause, reset, new generation, FPS display, etc.) to easily explore the dynamics of the system.
Home-page: https://github.com/thib1984/pybirdsreynolds
Author: thib1984
Author-email: thibault.garcon@gmail.com
License: MIT
Classifier: Programming Language :: Python :: 3.7
Classifier: Programming Language :: Python :: 3.8
Classifier: Programming Language :: Python :: 3.9
Classifier: Programming Language :: Python :: 3.10
Classifier: Programming Language :: Python :: 3.11
Classifier: Programming Language :: Python :: 3.12
Classifier: License :: OSI Approved :: MIT License
Classifier: Operating System :: OS Independent
Requires-Python: >=3.7
Requires-Dist: scipy
Dynamic: author
Dynamic: author-email
Dynamic: classifier
Dynamic: description
Dynamic: description-content-type
Dynamic: home-page
Dynamic: license
Dynamic: requires-dist
Dynamic: requires-python
Dynamic: summary
